[
    {
        "address": "0x118A28",
        "data": "00 00 80 D2 C0 03 5F D6"
    },
    {
        "address": "0x17E640",
        "data": "00 00 80 D2 C0 03 5F D6"
    },
    {
        "address": "0x1EDCB0",
        "data": "00 00 80 D2 C0 03 5F D6"
    },
    {
        "address": "0x1F7FE8",
        "data": "00 00 80 D2 C0 03 5F D6"
    },
    {
        "address": "0x21A2E0",
        "data": "00 00 80 D2 C0 03 5F D6"
    },
    {
        "address": "0x21A2E8",
        "data": "00 00 80 D2 C0 03 5F D6"
    },
    {
        "address": "0x21AD08",
        "data": "00 00 80 D2 C0 03 5F D6"
    },
    {
        "address": "0x23F7E8",
        "data": "00 00 80 D2 C0 03 5F D6"
    },
    {
        "address": "0x23F7F0",
        "data": "00 00 80 D2 C0 03 5F D6"
    },
    {
        "address": "0x2404E0",
        "data": "00 00 80 D2 C0 03 5F D6"
    },
    {
        "address": "0x240BA0",
        "data": "00 00 80 D2 C0 03 5F D6"
    },
    {
        "address": "0x240BA8",
        "data": "00 00 80 D2 C0 03 5F D6"
    },
    {
        "address": "0x23F7F0",
        "data": "00 00 80 D2 C0 03 5F D6"
    },
    {
        "address": "0x28958C",
        "data": "00 00 80 D2 C0 03 5F D6"
    },
    {
        "address": "0x27A8E8",
        "data": "00 00 80 D2 C0 03 5F D6"
    },
    {
        "address": "0x2778FC",
        "data": "00 00 80 D2 C0 03 5F D6"
    },
    {
        "address": "0x26594C",
        "data": "00 00 80 D2 C0 03 5F D6"
    },
    {
        "address": "0x2607E0",
        "data": "00 00 80 D2 C0 03 5F D6"
    },
    {
        "address": "0x25F3D4",
        "data": "00 00 80 D2 C0 03 5F D6"
    },
    {
        "address": "0x25F250",
        "data": "00 00 80 D2 C0 03 5F D6"
    },
    {
        "address": "0x255DF8",
        "data": "00 00 80 D2 C0 03 5F D6"
    },
    {
        "address": "0x24A648",
        "data": "00 00 80 D2 C0 03 5F D6"
    },
    {
        "address": "0x245DD4",
        "data": "00 00 80 D2 C0 03 5F D6"
    },
    {
        "address": "0x23F824",
        "data": "00 00 80 D2 C0 03 5F D6"
    },
    {
        "address": "0x23F7EC",
        "data": "00 00 80 D2 C0 03 5F D6"
    },
    {
        "address": "0x23A3FC",
        "data": "00 00 80 D2 C0 03 5F D6"
    },
    {
        "address": "0x2394B0",
        "data": "00 00 80 D2 C0 03 5F D6"
    },
    {
        "address": "0x2200E8",
        "data": "00 00 80 D2 C0 03 5F D6"
    },
    {
        "address": "0x255DF8",
        "data": "00 00 80 D2 C0 03 5F D6"
    }
]
